{
  "LTC": {
    "symbol": "LTC",
    "spread": 1.8060322799155302,
    "n_days": 30,
    "h": {
      "5": {
        "n": 10002404,
        "maker": {
          "floor": 4.0,
          "freq": 0.016288984128215576,
          "cond_mean": 6.672574973831617,
          "net_trade": 2.672574973831617,
          "trades_day": 281.4736457355652,
          "bp_day": 752.2594213860181
        },
        "taker": {
          "floor": 11.80603227991553,
          "freq": 0.0006710386823007749,
          "cond_mean": 15.8453497408186,
          "net_trade": 4.039317460903069,
          "trades_day": 11.59554843015739,
          "bp_day": 46.83810124268191
        }
      },
      "15": {
        "n": 9995778,
        "maker": {
          "floor": 4.0,
          "freq": 0.0644559132865896,
          "cond_mean": 6.9676876081776795,
          "net_trade": 2.9676876081776795,
          "trades_day": 371.26606053075614,
          "bp_day": 1101.8016871740695
        },
        "taker": {
          "floor": 11.80603227991553,
          "freq": 0.0037345767382989097,
          "cond_mean": 16.080183851215853,
          "net_trade": 4.274151571300322,
          "trades_day": 21.51116201260172,
          "bp_day": 91.94196691665746
        }
      },
      "30": {
        "n": 9989574,
        "maker": {
          "floor": 4.0,
          "freq": 0.13811469838453572,
          "cond_mean": 7.39564397083203,
          "net_trade": 3.3956439708320296,
          "trades_day": 397.77033134746284,
          "bp_day": 1350.686427415871
        },
        "taker": {
          "floor": 11.80603227991553,
          "freq": 0.011048819499209876,
          "cond_mean": 16.41863531576657,
          "net_trade": 4.612603035851038,
          "trades_day": 31.820600157724442,
          "bp_day": 146.77579689012182
        }
      },
      "60": {
        "n": 9982799,
        "maker": {
          "floor": 4.0,
          "freq": 0.25315374976497074,
          "cond_mean": 8.13653076313677,
          "net_trade": 4.13653076313677,
          "trades_day": 364.5413996615579,
          "bp_day": 1507.9367141369703
        },
        "taker": {
          "floor": 11.80603227991553,
          "freq": 0.031649340029785235,
          "cond_mean": 16.833134110310915,
          "net_trade": 5.0271018303953845,
          "trades_day": 45.57504964289074,
          "bp_day": 229.11041548013657
        }
      }
    }
  },
  "BNB": {
    "symbol": "BNB",
    "spread": 0.15998730136199243,
    "n_days": 30,
    "h": {
      "5": {
        "n": 10115058,
        "maker": {
          "floor": 4.0,
          "freq": 0.01071649811597719,
          "cond_mean": 5.938701646760031,
          "net_trade": 1.9387016467600313,
          "trades_day": 185.18108744408582,
          "bp_day": 359.0108791766626
        },
        "taker": {
          "floor": 10.159987301361992,
          "freq": 0.0006645537771508577,
          "cond_mean": 14.740010322283563,
          "net_trade": 4.580023020921571,
          "trades_day": 11.483489269166821,
          "bp_day": 52.59464521328986
        }
      },
      "15": {
        "n": 10108172,
        "maker": {
          "floor": 4.0,
          "freq": 0.05058966151347642,
          "cond_mean": 5.978857644542583,
          "net_trade": 1.9788576445425834,
          "trades_day": 291.3964503176242,
          "bp_day": 576.6320933036037
        },
        "taker": {
          "floor": 10.159987301361992,
          "freq": 0.0029192221897292605,
          "cond_mean": 14.947474358871773,
          "net_trade": 4.7874870575097805,
          "trades_day": 16.81471981284054,
          "bp_day": 80.50025347962739
        }
      },
      "30": {
        "n": 10101725,
        "maker": {
          "floor": 4.0,
          "freq": 0.11864102418151355,
          "cond_mean": 6.297520603214655,
          "net_trade": 2.2975206032146547,
          "trades_day": 341.686149642759,
          "bp_day": 785.0309686373242
        },
        "taker": {
          "floor": 10.159987301361992,
          "freq": 0.008565269793030399,
          "cond_mean": 14.742635932504122,
          "net_trade": 4.5826486311421295,
          "trades_day": 24.667977003927547,
          "bp_day": 113.04467105009415
        }
      },
      "60": {
        "n": 10094566,
        "maker": {
          "floor": 4.0,
          "freq": 0.2293277393005306,
          "cond_mean": 6.925613728104259,
          "net_trade": 2.925613728104259,
          "trades_day": 330.2319445927641,
          "bp_day": 966.1311105591558
        },
        "taker": {
          "floor": 10.159987301361992,
          "freq": 0.025889473603917197,
          "cond_mean": 14.79873108986028,
          "net_trade": 4.638743788498287,
          "trades_day": 37.28084198964076,
          "bp_day": 172.9362742094322
        }
      }
    }
  },
  "DOGE": {
    "symbol": "DOGE",
    "spread": 1.0210377589981166,
    "n_days": 30,
    "h": {
      "5": {
        "n": 9992591,
        "maker": {
          "floor": 4.0,
          "freq": 0.061225161722320065,
          "cond_mean": 6.2407214742619574,
          "net_trade": 2.2407214742619574,
          "trades_day": 1057.9707945616908,
          "bp_day": 2370.6178785163665
        },
        "taker": {
          "floor": 11.021037758998116,
          "freq": 0.003493488325500363,
          "cond_mean": 16.57782551481026,
          "net_trade": 5.556787755812145,
          "trades_day": 60.36747826464627,
          "bp_day": 335.44926407024235
        }
      },
      "15": {
        "n": 9983509,
        "maker": {
          "floor": 4.0,
          "freq": 0.19012172974452168,
          "cond_mean": 6.801378856770052,
          "net_trade": 2.801378856770052,
          "trades_day": 1095.101163328445,
          "bp_day": 3067.793244972592
        },
        "taker": {
          "floor": 11.021037758998116,
          "freq": 0.016447323280822403,
          "cond_mean": 16.488290513166103,
          "net_trade": 5.467252754167987,
          "trades_day": 94.73658209753704,
          "bp_day": 517.9488393932211
        }
      },
      "30": {
        "n": 9977250,
        "maker": {
          "floor": 4.0,
          "freq": 0.3247075095843043,
          "cond_mean": 7.561263323952198,
          "net_trade": 3.561263323952198,
          "trades_day": 935.1576276027963,
          "bp_day": 3330.3425612959854
        },
        "taker": {
          "floor": 11.021037758998116,
          "freq": 0.04298048059334987,
          "cond_mean": 16.787888523022318,
          "net_trade": 5.766850764024202,
          "trades_day": 123.78378410884763,
          "bp_day": 713.8426099619148
        }
      },
      "60": {
        "n": 9970140,
        "maker": {
          "floor": 4.0,
          "freq": 0.4716865560563844,
          "cond_mean": 8.82998602734626,
          "net_trade": 4.82998602734626,
          "trades_day": 679.2286407211935,
          "bp_day": 3280.664844056758
        },
        "taker": {
          "floor": 11.021037758998116,
          "freq": 0.10053419510658827,
          "cond_mean": 17.57559088570202,
          "net_trade": 6.5545531267039046,
          "trades_day": 144.7692409534871,
          "bp_day": 948.8976809422298
        }
      }
    }
  },
  "XRP": {
    "symbol": "XRP",
    "spread": 0.7144392103603312,
    "n_days": 30,
    "h": {
      "5": {
        "n": 10156973,
        "maker": {
          "floor": 4.0,
          "freq": 0.02976044142285305,
          "cond_mean": 5.859525431108204,
          "net_trade": 1.859525431108204,
          "trades_day": 514.2604277869007,
          "bp_day": 956.280343682326
        },
        "taker": {
          "floor": 10.71443921036033,
          "freq": 0.0012524400724507193,
          "cond_mean": 15.99338287404574,
          "net_trade": 5.278943663685409,
          "trades_day": 21.642164451948428,
          "bp_day": 114.24776690205077
        }
      },
      "15": {
        "n": 10146461,
        "maker": {
          "floor": 4.0,
          "freq": 0.10730628147094834,
          "cond_mean": 6.286448642669598,
          "net_trade": 2.2864486426695976,
          "trades_day": 618.0841812726625,
          "bp_day": 1413.2177373264287
        },
        "taker": {
          "floor": 10.71443921036033,
          "freq": 0.006524048138557868,
          "cond_mean": 15.52722312336922,
          "net_trade": 4.812783913008889,
          "trades_day": 37.578517278093315,
          "bp_day": 180.8572834307341
        }
      },
      "30": {
        "n": 10140245,
        "maker": {
          "floor": 4.0,
          "freq": 0.2055880306639534,
          "cond_mean": 6.839241576012927,
          "net_trade": 2.8392415760129266,
          "trades_day": 592.0935283121858,
          "bp_day": 1681.0965624721446
        },
        "taker": {
          "floor": 10.71443921036033,
          "freq": 0.019130602860187303,
          "cond_mean": 15.561108885375257,
          "net_trade": 4.846669675014926,
          "trades_day": 55.09613623733944,
          "bp_day": 267.03277271200415
        }
      },
      "60": {
        "n": 10133567,
        "maker": {
          "floor": 4.0,
          "freq": 0.3343111068392798,
          "cond_mean": 7.771245810715471,
          "net_trade": 3.771245810715471,
          "trades_day": 481.4079938485629,
          "bp_day": 1815.507880046332
        },
        "taker": {
          "floor": 10.71443921036033,
          "freq": 0.051892487610729766,
          "cond_mean": 16.074496565797762,
          "net_trade": 5.360057355437432,
          "trades_day": 74.72518215945087,
          "bp_day": 400.5312622701665
        }
      }
    }
  },
  "LINK": {
    "symbol": "LINK",
    "spread": 1.0777132315481084,
    "n_days": 30,
    "h": {
      "5": {
        "n": 10179288,
        "maker": {
          "floor": 4.0,
          "freq": 0.055962656720194966,
          "cond_mean": 6.0263915786933255,
          "net_trade": 2.0263915786933255,
          "trades_day": 967.034708124969,
          "bp_day": 1959.5909888485944
        },
        "taker": {
          "floor": 11.077713231548108,
          "freq": 0.0026171771542371136,
          "cond_mean": 15.86734537143568,
          "net_trade": 4.789632139887573,
          "trades_day": 45.224821225217326,
          "bp_day": 216.61025726097049
        }
      },
      "15": {
        "n": 10174672,
        "maker": {
          "floor": 4.0,
          "freq": 0.1744129933623413,
          "cond_mean": 6.617480061373781,
          "net_trade": 2.617480061373781,
          "trades_day": 1004.618841767086,
          "bp_day": 2629.5697876057698
        },
        "taker": {
          "floor": 11.077713231548108,
          "freq": 0.013162095053285255,
          "cond_mean": 16.132424330898846,
          "net_trade": 5.0547110993507385,
          "trades_day": 75.81366750692307,
          "bp_day": 383.2161866297306
        }
      },
      "30": {
        "n": 10170046,
        "maker": {
          "floor": 4.0,
          "freq": 0.30031044107371785,
          "cond_mean": 7.34649777040719,
          "net_trade": 3.34649777040719,
          "trades_day": 864.8940702923074,
          "bp_day": 2894.3660778716057
        },
        "taker": {
          "floor": 11.077713231548108,
          "freq": 0.03523189570627311,
          "cond_mean": 16.599575890536485,
          "net_trade": 5.521862658988377,
          "trades_day": 101.46785963406656,
          "bp_day": 560.2915852008259
        }
      },
      "60": {
        "n": 10162846,
        "maker": {
          "floor": 4.0,
          "freq": 0.44103541468600427,
          "cond_mean": 8.544969770265054,
          "net_trade": 4.5449697702650536,
          "trades_day": 635.0909971478461,
          "bp_day": 2886.46938340445
        },
        "taker": {
          "floor": 11.077713231548108,
          "freq": 0.08342112042236988,
          "cond_mean": 17.518157496697906,
          "net_trade": 6.440444265149798,
          "trades_day": 120.12641340821263,
          "bp_day": 773.6674703279367
        }
      }
    }
  },
  "SOL": {
    "symbol": "SOL",
    "spread": 1.174467231363076,
    "n_days": 30,
    "h": {
      "5": {
        "n": 9858346,
        "maker": {
          "floor": 4.0,
          "freq": 0.03612451825083031,
          "cond_mean": 6.385788017271988,
          "net_trade": 2.385788017271988,
          "trades_day": 624.2316753743478,
          "bp_day": 1489.2844511097362
        },
        "taker": {
          "floor": 11.174467231363076,
          "freq": 0.0020847310492044,
          "cond_mean": 16.01494654596082,
          "net_trade": 4.840479314597745,
          "trades_day": 36.02415253025203,
          "bp_day": 174.37416514859902
        }
      },
      "15": {
        "n": 9846153,
        "maker": {
          "floor": 4.0,
          "freq": 0.1257819170593835,
          "cond_mean": 6.812725956508581,
          "net_trade": 2.812725956508581,
          "trades_day": 724.5038422620489,
          "bp_day": 2037.8307627206636
        },
        "taker": {
          "floor": 11.174467231363076,
          "freq": 0.009687438332514231,
          "cond_mean": 15.998102951535504,
          "net_trade": 4.823635720172428,
          "trades_day": 55.79964479528197,
          "bp_day": 269.1571598074557
        }
      },
      "30": {
        "n": 9840181,
        "maker": {
          "floor": 4.0,
          "freq": 0.23424294736041948,
          "cond_mean": 7.45786422142792,
          "net_trade": 3.4578642214279203,
          "trades_day": 674.6196883980081,
          "bp_day": 2332.743283582325
        },
        "taker": {
          "floor": 11.174467231363076,
          "freq": 0.027417889975804306,
          "cond_mean": 16.192262660886637,
          "net_trade": 5.017795429523561,
          "trades_day": 78.9635231303164,
          "bp_day": 396.2228054623795
        }
      },
      "60": {
        "n": 9833118,
        "maker": {
          "floor": 4.0,
          "freq": 0.37024685354126735,
          "cond_mean": 8.529637480100158,
          "net_trade": 4.529637480100158,
          "trades_day": 533.155469099425,
          "bp_day": 2415.000995553138
        },
        "taker": {
          "floor": 11.174467231363076,
          "freq": 0.06940362151659321,
          "cond_mean": 16.944763205043458,
          "net_trade": 5.770295973680382,
          "trades_day": 99.94121498389423,
          "bp_day": 576.6903904262902
        }
      }
    }
  },
  "BTC": {
    "symbol": "BTC",
    "spread": 0.01316137239714176,
    "n_days": 30,
    "h": {
      "5": {
        "n": 10322440,
        "maker": {
          "floor": 4.0,
          "freq": 0.024567253478828648,
          "cond_mean": 6.019829493080337,
          "net_trade": 2.019829493080337,
          "trades_day": 424.522140114159,
          "bp_day": 857.462339068162
        },
        "taker": {
          "floor": 10.01316137239714,
          "freq": 0.0015682338671864403,
          "cond_mean": 14.095607742187035,
          "net_trade": 4.082446369789894,
          "trades_day": 27.09908122498169,
          "bp_day": 110.63054577156797
        }
      },
      "15": {
        "n": 10315363,
        "maker": {
          "floor": 4.0,
          "freq": 0.09365971900358717,
          "cond_mean": 6.409336773615778,
          "net_trade": 2.4093367736157782,
          "trades_day": 539.4799814606621,
          "bp_day": 1299.788957962731
        },
        "taker": {
          "floor": 10.01316137239714,
          "freq": 0.008013193525036395,
          "cond_mean": 14.43565946172377,
          "net_trade": 4.422498089326629,
          "trades_day": 46.15599470420963,
          "bp_day": 204.12479839033705
        }
      },
      "30": {
        "n": 10311465,
        "maker": {
          "floor": 4.0,
          "freq": 0.18251334800632113,
          "cond_mean": 6.947170825248189,
          "net_trade": 2.9471708252481887,
          "trades_day": 525.6384422582048,
          "bp_day": 1549.1462816522858
        },
        "taker": {
          "floor": 10.01316137239714,
          "freq": 0.022305656858651997,
          "cond_mean": 14.70582298941337,
          "net_trade": 4.692661617016229,
          "trades_day": 64.24029175291776,
          "bp_day": 301.4579513748413
        }
      },
      "60": {
        "n": 10307918,
        "maker": {
          "floor": 4.0,
          "freq": 0.3025907850644524,
          "cond_mean": 7.837547377554983,
          "net_trade": 3.8375473775549827,
          "trades_day": 435.73073049281146,
          "bp_day": 1672.1373221228055
        },
        "taker": {
          "floor": 10.01316137239714,
          "freq": 0.05747998771429885,
          "cond_mean": 15.234204569026824,
          "net_trade": 5.221043196629683,
          "trades_day": 82.77118230859034,
          "bp_day": 432.15191826926105
        }
      }
    }
  },
  "ETH": {
    "symbol": "ETH",
    "spread": 0.043218295221418915,
    "n_days": 30,
    "h": {
      "5": {
        "n": 10343992,
        "maker": {
          "floor": 4.0,
          "freq": 0.044102702322275575,
          "cond_mean": 6.3680989724535255,
          "net_trade": 2.3680989724535255,
          "trades_day": 762.0946961289219,
          "bp_day": 1804.7156668151822
        },
        "taker": {
          "floor": 10.043218295221418,
          "freq": 0.0038049140022536755,
          "cond_mean": 14.822527009755113,
          "net_trade": 4.779308714533695,
          "trades_day": 65.74891395894352,
          "bp_day": 314.2343574551048
        }
      },
      "15": {
        "n": 10340117,
        "maker": {
          "floor": 4.0,
          "freq": 0.14225883517565613,
          "cond_mean": 6.879633656566949,
          "net_trade": 2.8796336565669494,
          "trades_day": 819.4108906117793,
          "bp_day": 2359.6031791631785
        },
        "taker": {
          "floor": 10.043218295221418,
          "freq": 0.016609386528218202,
          "cond_mean": 15.11963053127224,
          "net_trade": 5.076412236050821,
          "trades_day": 95.67006640253685,
          "bp_day": 485.6606957096325
        }
      },
      "30": {
        "n": 10337112,
        "maker": {
          "floor": 4.0,
          "freq": 0.25250166584245193,
          "cond_mean": 7.554340654417407,
          "net_trade": 3.554340654417407,
          "trades_day": 727.2047976262616,
          "bp_day": 2584.733576290406
        },
        "taker": {
          "floor": 10.043218295221418,
          "freq": 0.041311441725696695,
          "cond_mean": 15.465491361026164,
          "net_trade": 5.422273065804745,
          "trades_day": 118.97695217000648,
          "bp_day": 645.1255232029656
        }
      },
      "60": {
        "n": 10333137,
        "maker": {
          "floor": 4.0,
          "freq": 0.38314715076360645,
          "cond_mean": 8.680000854772238,
          "net_trade": 4.6800008547722385,
          "trades_day": 551.7318970995933,
          "bp_day": 2582.105750031205
        },
        "taker": {
          "floor": 10.043218295221418,
          "freq": 0.09309167196757384,
          "cond_mean": 16.246622166927345,
          "net_trade": 6.203403871705927,
          "trades_day": 134.05200763330635,
          "bp_day": 831.5787431624047
        }
      }
    }
  }
}